ODP_DQ/AnomalyDetectionNB.py
ODP_DQ/StandardizationNB.py
ODP_DQ/__init__.py
ODP_DQ/__main__.py
ODP_DQ/business_contextNB.py
ODP_DQ-1.0.53.dist-info/LICENSE
ODP_DQ-1.0.53.dist-info/METADATA
ODP_DQ-1.0.53.dist-info/WHEEL
ODP_DQ-1.0.53.dist-info/top_level.txt
ODP_DQ-1.0.53.dist-info/RECORD
